Vlue-0.1.1.data/scripts/vlue.py
astor/__init__.py
astor/code_gen.py
astor/codegen.py
astor/file_util.py
astor/node_util.py
astor/op_util.py
astor/rtrip.py
astor/source_repr.py
astor/string_repr.py
astor/tree_walk.py
lib/Web.py
lib/__init__.py
lib/base.py
lib/random.py
ply/__init__.py
ply/lex.py
ply/yacc.py
Vlue-0.1.1.dist-info/LICENSE
Vlue-0.1.1.dist-info/METADATA
Vlue-0.1.1.dist-info/WHEEL
Vlue-0.1.1.dist-info/top_level.txt
Vlue-0.1.1.dist-info/RECORD
